villaThinClient/__init__.py
villaThinClient/_nbdev.py
villaThinClient/migration.py
villaThinClient/shopping.py
villaThinClient-0.0.1.dist-info/LICENSE
villaThinClient-0.0.1.dist-info/METADATA
villaThinClient-0.0.1.dist-info/WHEEL
villaThinClient-0.0.1.dist-info/entry_points.txt
villaThinClient-0.0.1.dist-info/top_level.txt
villaThinClient-0.0.1.dist-info/RECORD
