Metadata-Version: 2.1
Name: villaThinClient
Version: 0.0.1
Summary: send line message notification, support aws  lambda
Home-page: https://github.com/thanakijwanavit/linesdk/tree/master/
Author: nic wanavit
Author-email: nwanavit@hatari.cc
License: Apache Software License 2.0
Keywords: linesdk
Platform: UNKNOWN
Classifier: Development Status :: 3 - Alpha
Classifier: Intended Audience :: Developers
Classifier: License :: OSI Approved :: Apache Software License
Classifier: Natural Language :: English
Classifier: Programming Language :: Python :: 3.6
Classifier: Programming Language :: Python :: 3.7
Classifier: Programming Language :: Python :: 3.8
Requires-Python: >=3.6
Requires-Dist: requests
Requires-Dist: line-bot-sdk
Requires-Dist: lambdasdk
